bem_helmholtz_3d/__init__.py
bem_helmholtz_3d/__main__.py
bem_helmholtz_3d/cli.py
bem_helmholtz_3d/main.py
bem_helmholtz_3d/py.typed
bem_helmholtz_3d-1.0.0.dist-info/licenses/LICENSE
bem_helmholtz_3d-1.0.0.dist-info/METADATA
bem_helmholtz_3d-1.0.0.dist-info/WHEEL
bem_helmholtz_3d-1.0.0.dist-info/entry_points.txt
bem_helmholtz_3d-1.0.0.dist-info/top_level.txt
bem_helmholtz_3d-1.0.0.dist-info/RECORD
