Metadata-Version: 2.4
Name: bem-helmholtz-3d
Version: 1.0.0
Summary: 3D BEM for Helmholtz equation
Author-email: 34j <34j.95a2p@simplelogin.com>
License: MIT
Project-URL: Bug Tracker, https://github.com/34j/bem-helmholtz-3d/issues
Project-URL: Changelog, https://github.com/34j/bem-helmholtz-3d/blob/main/CHANGELOG.md
Project-URL: documentation, https://bem-helmholtz-3d.readthedocs.io
Project-URL: repository, https://github.com/34j/bem-helmholtz-3d
Classifier: Development Status :: 2 - Pre-Alpha
Classifier: Intended Audience :: Developers
Classifier: Natural Language :: English
Classifier: Operating System :: OS Independent
Classifier: Programming Language :: Python :: 3.9
Classifier: Programming Language :: Python :: 3.10
Classifier: Programming Language :: Python :: 3.11
Classifier: Programming Language :: Python :: 3.12
Classifier: Programming Language :: Python :: 3.13
Classifier: Topic :: Software Development :: Libraries
Requires-Python: >=3.9
License-File: LICENSE
Requires-Dist: rich>=10
Requires-Dist: typer<1,>=0.15
Dynamic: license-file
